classification_pipeline/__init__.py
classification_pipeline/classification.py
classification_pipeline-0.432.dist-info/LICENSE
classification_pipeline-0.432.dist-info/METADATA
classification_pipeline-0.432.dist-info/WHEEL
classification_pipeline-0.432.dist-info/top_level.txt
classification_pipeline-0.432.dist-info/RECORD
