Metadata-Version: 2.1
Name: classification-pipeline
Version: 0.432
Summary: Declaratively configured pipeline for image classification
Home-page: https://github.com/musket-ml/classification_training_pipeline
Author: Petrochenko Pavel
Author-email: petrochenko.pavel.a@gmail.com
License: MIT
Platform: UNKNOWN
Requires-Dist: musket-core
